paddle_spline_conv/__init__.py
paddle_spline_conv/functional.py
paddle_spline_conv/nn.py
paddle_spline_conv/ops.py
paddle_spline_conv-0.0.2.dist-info/METADATA
paddle_spline_conv-0.0.2.dist-info/WHEEL
paddle_spline_conv-0.0.2.dist-info/top_level.txt
paddle_spline_conv-0.0.2.dist-info/RECORD
