Metadata-Version: 2.1
Name: paddle-spline-conv
Version: 0.0.2
Summary: SplineConv module for paddle.
Home-page: https://github.com/eliphatfs/paddle-spline-conv
Author: flandre.info
Author-email: flandre@scarletx.cn
License: UNKNOWN
Platform: UNKNOWN
Classifier: Programming Language :: Python :: 3 :: Only
Classifier: License :: OSI Approved :: Apache Software License
Classifier: Operating System :: OS Independent
Requires-Python: ~=3.6
